odoo/addons/l10n_fr_pos_caisse_ap_ip/README.rst
odoo/addons/l10n_fr_pos_caisse_ap_ip/__init__.py
odoo/addons/l10n_fr_pos_caisse_ap_ip/__manifest__.py
odoo/addons/l10n_fr_pos_caisse_ap_ip/i18n/fr.po
odoo/addons/l10n_fr_pos_caisse_ap_ip/i18n/l10n_fr_pos_caisse_ap_ip.pot
odoo/addons/l10n_fr_pos_caisse_ap_ip/models/__init__.py
odoo/addons/l10n_fr_pos_caisse_ap_ip/models/pos_payment_method.py
odoo/addons/l10n_fr_pos_caisse_ap_ip/readme/CONFIGURE.rst
odoo/addons/l10n_fr_pos_caisse_ap_ip/readme/CONTRIBUTORS.rst
odoo/addons/l10n_fr_pos_caisse_ap_ip/readme/CREDITS.rst
odoo/addons/l10n_fr_pos_caisse_ap_ip/readme/DESCRIPTION.rst
odoo/addons/l10n_fr_pos_caisse_ap_ip/static/description/icon.png
odoo/addons/l10n_fr_pos_caisse_ap_ip/static/description/index.html
odoo/addons/l10n_fr_pos_caisse_ap_ip/static/src/js/models.js
odoo/addons/l10n_fr_pos_caisse_ap_ip/static/src/js/payment_caisse_ap_ip.js
odoo/addons/l10n_fr_pos_caisse_ap_ip/views/assets.xml
odoo/addons/l10n_fr_pos_caisse_ap_ip/views/pos_payment_method.xml
odoo14_addon_l10n_fr_pos_caisse_ap_ip-14.0.1.4.0.dist-info/METADATA
odoo14_addon_l10n_fr_pos_caisse_ap_ip-14.0.1.4.0.dist-info/WHEEL
odoo14_addon_l10n_fr_pos_caisse_ap_ip-14.0.1.4.0.dist-info/top_level.txt
odoo14_addon_l10n_fr_pos_caisse_ap_ip-14.0.1.4.0.dist-info/RECORD
