Metadata-Version: 2.1
Name: odoo14-addon-l10n_fr_pos_caisse_ap_ip
Version: 14.0.1.4.0
Summary: Add support for Caisse-AP payment protocol used in France
Home-page: https://github.com/OCA/l10n-france
Author: Akretion,Odoo Community Association (OCA)
Author-email: support@odoo-community.org
License: AGPL-3
Classifier: Programming Language :: Python
Classifier: Framework :: Odoo
Classifier: Framework :: Odoo :: 14.0
Classifier: License :: OSI Approved :: GNU Affero General Public License v3
Requires-Python: >=3.6
Requires-Dist: odoo<14.1dev,>=14.0a
